setup.py
invoicing/__init__.py
invoicing/invoice.py
invoicing_Excel_PDF_2023.egg-info/PKG-INFO
invoicing_Excel_PDF_2023.egg-info/SOURCES.txt
invoicing_Excel_PDF_2023.egg-info/dependency_links.txt
invoicing_Excel_PDF_2023.egg-info/requires.txt
invoicing_Excel_PDF_2023.egg-info/top_level.txt